MANIFEST.in
README.rst
setup.cfg
setup.py
VisualPortfolio/Env.py
VisualPortfolio/Miscellaneous.py
VisualPortfolio/Plottings.py
VisualPortfolio/Tears.py
VisualPortfolio/Timeseries.py
VisualPortfolio/Transactions.py
VisualPortfolio/__init__.py
VisualPortfolio.egg-info/PKG-INFO
VisualPortfolio.egg-info/SOURCES.txt
VisualPortfolio.egg-info/dependency_links.txt
VisualPortfolio.egg-info/requires.txt
VisualPortfolio.egg-info/top_level.txt
img/1.png
img/2.png
img/3.png
img/4.png
requirements/py2.txt
requirements/py3.txt