Metadata-Version: 1.0
Name: VisualPortfolio
Version: 0.2.4
Summary: VisualPortfolio 0.2.4
Home-page: https://github.com/ChinaQuants/VisualPortfolio
Author: cheng li
Author-email: wegamekinglc@hotmail.com
License: UNKNOWN
Platform: UNKNOWN
